testari/__init__.py
testari/__main__.py
testari/py.typed
testari-0.0.1.dist-info/LICENSE
testari-0.0.1.dist-info/WHEEL
testari-0.0.1.dist-info/METADATA
testari-0.0.1.dist-info/RECORD
